LICENSE
README.md
setup.py
HealthCheckIOAPI.egg-info/PKG-INFO
HealthCheckIOAPI.egg-info/SOURCES.txt
HealthCheckIOAPI.egg-info/dependency_links.txt
HealthCheckIOAPI.egg-info/requires.txt
HealthCheckIOAPI.egg-info/top_level.txt
healthcheckio/__init__.py
healthcheckio/hc_log.py
healthcheckio/hc_ping.py