Metadata-Version: 2.1
Name: HealthCheckIOAPI
Version: 1.0.3
Summary: Simple Python Tooling to interact with Healthcheck.io projects.
Home-page: https://github.com/basegodfelix/healthcheckioapi
Author: Felix Hernandez
License: MIT
Platform: UNKNOWN
License-File: LICENSE
